garmi_parti/__init__.py
garmi_parti/_version.py
garmi_parti/_version.pyi
garmi_parti/py.typed
garmi_parti/assets/endeffector.obj
garmi_parti/assets/endeffector.xml
garmi_parti/assets/endeffector_ft.xml
garmi_parti/assets/ft.obj
garmi_parti/assets/parti_mmt.xml
garmi_parti/assets/pusher.obj
garmi_parti/assets/tip.obj
garmi_parti/garmi/__init__.py
garmi_parti/garmi/mmt.py
garmi_parti/launchers/__init__.py
garmi_parti/launchers/garmi_mmt.py
garmi_parti/launchers/garmi_teleop.py
garmi_parti/launchers/panda_teleop.py
garmi_parti/launchers/parti_haptic_sim.py
garmi_parti/launchers/parti_mmt.py
garmi_parti/launchers/parti_teleop.py
garmi_parti/panda/__init__.py
garmi_parti/parti/__init__.py
garmi_parti/parti/haptic_simulation.py
garmi_parti/parti/mmt.py
garmi_parti/peripherals/__init__.py
garmi_parti/peripherals/joystick.py
garmi_parti/teleoperation/__init__.py
garmi_parti/teleoperation/client.py
garmi_parti/teleoperation/containers.py
garmi_parti/teleoperation/interfaces.py
garmi_parti/teleoperation/server.py
garmi_parti/teleoperation/utils.py
garmi_parti-0.2.4.dist-info/METADATA
garmi_parti-0.2.4.dist-info/WHEEL
garmi_parti-0.2.4.dist-info/entry_points.txt
garmi_parti-0.2.4.dist-info/licenses/LICENSE
garmi_parti-0.2.4.dist-info/RECORD
