Metadata-Version: 2.3
Name: garmi-parti
Version: 0.2.4
Summary: Teleoperation between Garmi and Parti
Project-URL: Homepage, https://github.com/JeanElsner/garmi-parti
Project-URL: Bug Tracker, https://github.com/JeanElsner/garmi-parti/issues
Project-URL: Discussions, https://github.com/JeanElsner/garmi-parti/discussions
Project-URL: Changelog, https://github.com/JeanElsner/garmi-parti/releases
Author-email: Jean Elsner <jean.elsner@tum.de>
License: 
License-File: LICENSE
Classifier: Development Status :: 1 - Planning
Classifier: Intended Audience :: Developers
Classifier: Intended Audience :: Science/Research
Classifier: License :: OSI Approved :: Apache Software License
Classifier: Operating System :: OS Independent
Classifier: Programming Language :: Python
Classifier: Programming Language :: Python :: 3
Classifier: Programming Language :: Python :: 3 :: Only
Classifier: Programming Language :: Python :: 3.8
Classifier: Programming Language :: Python :: 3.9
Classifier: Programming Language :: Python :: 3.10
Classifier: Programming Language :: Python :: 3.11
Classifier: Programming Language :: Python :: 3.12
Classifier: Topic :: Scientific/Engineering
Classifier: Typing :: Typed
Requires-Python: <3.13,>=3.8
Requires-Dist: dm-robotics-panda>=0.4.7
Requires-Dist: panda-python>=0.7.5
Requires-Dist: pyserial
Requires-Dist: pyzmq
Requires-Dist: roslibpy
Requires-Dist: spatialmath-python
Provides-Extra: dev
Requires-Dist: pytest-cov>=3; extra == 'dev'
Requires-Dist: pytest>=6; extra == 'dev'
Provides-Extra: docs
Requires-Dist: furo>=2023.08.17; extra == 'docs'
Requires-Dist: myst-parser>=0.13; extra == 'docs'
Requires-Dist: sphinx-autodoc-typehints; extra == 'docs'
Requires-Dist: sphinx-copybutton; extra == 'docs'
Requires-Dist: sphinx>=7.0; extra == 'docs'
Provides-Extra: test
Requires-Dist: pytest-cov>=3; extra == 'test'
Requires-Dist: pytest>=6; extra == 'test'
